{
  "variables": {
    "priority": ["children", "tile", "data", "priority"]
  },
  "contents": {
    "type": "Node",
    "format": {
      "type": "Anchored"
    },
    "data": {
      "anchor": [0, 0],
      "size": [48, 48]
    },
    "layout": {
      "x_anchor": "left",
      "y_anchor": "bottom"
    },
    "children": {
      "leaves": {
        "type": "Image",
        "data": {
          "texture": "tile-tree-leaves",
          "anchor": [0.5, 0.5],
          "priority": 340282300000000000000000000000000000000
        },
        "layout": {
          "x_anchor": "center",
          "y_anchor": "middle",
          "y_offset": 15,
          "absolute": true
        }
      },
      "tile": {
        "type": "Wall",
        "data": {
          "texture": "tile-tree",
          "anchor": [0.5, 0.5],
          "priority": 0,
          "obstacle": [0, 6, 48, 6, 48, 42, 0, 42]
        },
        "layout": {
          "x_anchor": "center",
          "y_anchor": "middle",
          "y_offset": 15,
          "absolute": true
        }
      },
      "shadow": {
        "type": "Image",
        "data": {
          "texture": "tile-tree-shadow",
          "anchor": [0.5, 0.5],
          "priority": -0.9
        },
        "layout": {
          "x_anchor": "center",
          "y_anchor": "middle",
          "y_offset": 15,
          "absolute": true
        }
      },
      "floor": {
        "type": "Widget",
        "data": {
          "key": "tile-1",
          "variables": {}
        }
      }
    }
  }
}